mbtest/__init__.py
mbtest/matchers.py
mbtest/py.typed
mbtest/server.py
mbtest/util.py
mbtest/imposters/__init__.py
mbtest/imposters/base.py
mbtest/imposters/imposters.py
mbtest/imposters/predicates.py
mbtest/imposters/responses.py
mbtest/imposters/stubs.py
mbtest/imposters/behaviors/__init__.py
mbtest/imposters/behaviors/copy.py
mbtest/imposters/behaviors/lookup.py
mbtest/imposters/behaviors/using.py
mbtest-2.14.0.dist-info/LICENSE
mbtest-2.14.0.dist-info/METADATA
mbtest-2.14.0.dist-info/WHEEL
mbtest-2.14.0.dist-info/top_level.txt
mbtest-2.14.0.dist-info/RECORD
