Metadata-Version: 2.1
Name: mbtest
Version: 2.14.0
Summary: Python wrapper & utils for the Mountebank over the wire test double tool.
Home-page: https://github.com/brunns/mbtest/
Author: Simon Brunning
Author-email: simon@brunn.ing
Classifier: Development Status :: 5 - Production/Stable
Classifier: Intended Audience :: Developers
Classifier: License :: OSI Approved :: MIT License
Classifier: Operating System :: OS Independent
Classifier: Programming Language :: Python
Classifier: Programming Language :: Python :: 3
Classifier: Programming Language :: Python :: 3.9
Classifier: Programming Language :: Python :: 3.10
Classifier: Programming Language :: Python :: 3.11
Classifier: Programming Language :: Python :: 3.12
Classifier: Programming Language :: Python :: 3.13
Classifier: Programming Language :: Python :: Implementation :: PyPy
Classifier: Topic :: Software Development :: Testing
Requires-Python: >=3.9
License-File: LICENSE
Requires-Dist: pyhamcrest>=2.0
Requires-Dist: Deprecated>=1.2
Requires-Dist: brunns-matchers>=2.9
Requires-Dist: yarl>=1.9
Requires-Dist: httpx>=0.28
Provides-Extra: coverage
Requires-Dist: pytest-cov>=2.5; extra == "coverage"
Requires-Dist: codacy-coverage>=1.0; extra == "coverage"
Provides-Extra: docs
Requires-Dist: sphinx>=3.0; extra == "docs"
Requires-Dist: sphinx-autodoc-typehints>=1.10; extra == "docs"
Requires-Dist: pytest>=6.0; extra == "docs"
Requires-Dist: furo; extra == "docs"
Provides-Extra: install
Requires-Dist: pyhamcrest>=2.0; extra == "install"
Requires-Dist: Deprecated>=1.2; extra == "install"
Requires-Dist: brunns-matchers>=2.9; extra == "install"
Requires-Dist: yarl>=1.9; extra == "install"
Requires-Dist: httpx>=0.28; extra == "install"
Provides-Extra: test
Requires-Dist: pytest>=6.0; extra == "test"
Requires-Dist: contexttimer>=0.3; extra == "test"
Requires-Dist: brunns-builder>=1.1; extra == "test"
Requires-Dist: trustme>=0.9; extra == "test"
Requires-Dist: furl>=2.0; extra == "test"
